noise2read/__init__.py
noise2read/classifier.py
noise2read/config.py
noise2read/coverage.py
noise2read/data_analysis.py
noise2read/data_generation.py
noise2read/data_preprocessing.py
noise2read/encoding.py
noise2read/error_orrection.py
noise2read/isolates_correction.py
noise2read/noise2read.py
noise2read/noise2readAPI.py
noise2read/reads2vectors.py
noise2read/simulation.py
noise2read/umitest.py
noise2read/utils.py
noise2read-0.3.0.dist-info/LICENSE
noise2read-0.3.0.dist-info/METADATA
noise2read-0.3.0.dist-info/WHEEL
noise2read-0.3.0.dist-info/entry_points.txt
noise2read-0.3.0.dist-info/top_level.txt
noise2read-0.3.0.dist-info/RECORD
