Metadata-Version: 2.1
Name: noise2read
Version: 0.3.0
Summary: Turn noise to read
Home-page: https://github.com/Jappy0/noise2read
Author: Penagyao Ping
Author-email: ping.pengyao@gmail.com
Classifier: Programming Language :: Python :: 3
Classifier: License :: OSI Approved :: MIT License
Classifier: Operating System :: OS Independent
Requires-Python: >=3.8
License-File: LICENSE
Requires-Dist: biopython ==1.79
Requires-Dist: xgboost ==1.6.1
Requires-Dist: Xlsxwriter >=3.0.3
Requires-Dist: scikit-learn >=1.1.1
Requires-Dist: networkx ==2.8.5
Requires-Dist: pandas >=1.4.3
Requires-Dist: optuna >=3.1.1
Requires-Dist: matplotlib >=3.5.2
Requires-Dist: mpire >=2.8.0
Requires-Dist: editdistance >=0.6.0
Requires-Dist: imbalanced-learn >=0.9.1
